README.rst
setup.py
pubg/__init__.py
pubg/constants.py
pubg/core.py
pubg/objects.py
pubg.egg-info/PKG-INFO
pubg.egg-info/SOURCES.txt
pubg.egg-info/dependency_links.txt
pubg.egg-info/requires.txt
pubg.egg-info/top_level.txt