Metadata-Version: 1.1
Name: pubg
Version: 0.0.3
Summary: Python wrapper for the Battlegrounds Developer API
Home-page: https://github.com/nicolaskenner/python-pubg-api-wrapper
Author: Nicolas Kenner
Author-email: nick@nicolaskenner.com
License: MIT
Platform: UNKNOWN
Classifier: Development Status :: 1 - Planning
Classifier: License :: OSI Approved :: MIT License
Classifier: Programming Language :: Python :: 3.6
